{
    "ArchiveScreen": {
        "TrainLabel": "Группа",
        "TrainArriveLabel": "Подана группа",
        "TrainDepartureLabel": "Убрана группа",
        "TotalTime": "Время загрузки: ",
        "ArrivedAt": "Подан в ",
        "DeparturedAt": "Убран в ",
        "TrainArrivedAt": "Группа подана в ",
        "TrainDeparturedAt": "Группа убрана в ",
        "Full": "Полный",
        "Empty": "Порожний",
        "Wagons1": "вагон",
        "Wagons234": "вагона",
        "Wagons50": "вагонов",
        "CurrentlyUnderLoading": "Сейчас в погрузке",
        "LoadTime": "Находился в погрузке"
    },
    "LogScreen": {
        "Wagon": "вагон",
        "Arrived": "прибыл на станцию.",
        "Departured": "ушёл со станции.",
        "Failed": "ОШИБКА. Нажмите для получения информации",
        "Damaged": "ЛОГ ПОВРЕЖДЁН",
        "Full": "Полный",
        "Empty": "Порожний",
        "HideLogs": "Скрыть логи",
        "ShowLogs": "Открыть логи"
    },
    "LiveScreen": {
        "WagonsNumber": "Номер вагона:",
        "WagonsState": "Состояние:",
        "CloseButton": "Закрыть",
        "ApplyButton": "Применить",
        "Fix": "ИСПРАВИТЬ",
        "EmptyState": "Порожний",
        "FullState": "Полный",
        "ErrorState": "Ошибка",
        "Wagon": "Вагон",
        "ArrivedAt": "прибыл в",
        "State": "состояние"
    },
    "ToolBar": {
        "TimeGone": "Время смены:",
        "WagonsGone": "Вагонов загружено:",
        "EmptyWagonsOnStation": "Порожних вагонов на станции",
        "FullWagonsOnStation": "Полных вагонов на станции",
        "LoadArea": "Участок погрузки",
        "Route": "путь",
        "Dispatcher": "Диспетчер"
    }
}